aiflows/__init__.py
aiflows/backends/__init__.py
aiflows/backends/api_info.py
aiflows/backends/llm_lite.py
aiflows/base_flows/__init__.py
aiflows/base_flows/abstract.py
aiflows/base_flows/atomic.py
aiflows/base_flows/composite.py
aiflows/configs/base_config.py
aiflows/configs/python_logger.yaml
aiflows/data_transformations/__init__.py
aiflows/data_transformations/abstract.py
aiflows/data_transformations/end_of_interaction.py
aiflows/data_transformations/json.py
aiflows/data_transformations/key_copy.py
aiflows/data_transformations/key_delete.py
aiflows/data_transformations/key_match_input.py
aiflows/data_transformations/key_rename.py
aiflows/data_transformations/key_select.py
aiflows/data_transformations/key_set.py
aiflows/data_transformations/print_previous_messages.py
aiflows/data_transformations/regex_extractor_first.py
aiflows/data_transformations/unnesting_dict.py
aiflows/datasets/__init__.py
aiflows/datasets/abstract.py
aiflows/datasets/demonstrations_11.py
aiflows/datasets/outputs.py
aiflows/flow_cache/__init__.py
aiflows/flow_cache/flow_cache.py
aiflows/flow_verse/__init__.py
aiflows/flow_verse/loading.py
aiflows/flow_verse/utils.py
aiflows/interfaces/__init__.py
aiflows/interfaces/abstract.py
aiflows/interfaces/key_interface.py
aiflows/messages/__init__.py
aiflows/messages/abstract.py
aiflows/messages/flow_message.py
aiflows/prompt_template/__init__.py
aiflows/prompt_template/jinja2_prompts.py
aiflows/utils/__init__.py
aiflows/utils/coflows_utils.py
aiflows/utils/colink_utils.py
aiflows/utils/constants.py
aiflows/utils/general_helpers.py
aiflows/utils/io_utils.py
aiflows/utils/logging.py
aiflows/utils/rich_utils.py
aiflows/utils/serving.py
aiflows/workers/__init__.py
aiflows/workers/dispatch_worker.py
aiflows/workers/get_instance_worker.py
flow_modules/__init__.py
flow_modules/aiflows/__init__.py
flow_modules/aiflows/ChatFlowModule/ChatAtomicFlow.py
flow_modules/aiflows/ChatFlowModule/__init__.py
flow_modules/aiflows/ChatFlowModule/run.py
aiflows-1.1.1.dist-info/LICENSE
aiflows-1.1.1.dist-info/METADATA
aiflows-1.1.1.dist-info/WHEEL
aiflows-1.1.1.dist-info/top_level.txt
aiflows-1.1.1.dist-info/RECORD
