Metadata-Version: 2.1
Name: aiflows
Version: 1.1.1
Summary: aiFlows implements the abstraction of Flows proposed in "Flows: Building Blocks of Reasoning and Collaborating AI" and greatly simplifies the design and implementation of complex (work)Flows involving humans, AI systems, and tools.
Author-email: Martin Josifoski <martin.josifoski@epfl.ch>, Nicolas Baldwin <nicolas.baldwin@epfl.ch>
License: MIT License
Project-URL: Home, https://epfl-dlab.github.io/aiflows/
Project-URL: Documentation, https://epfl-dlab.github.io/aiflows/docs/built_with_sphinx/html/index.html
Project-URL: Source, https://github.com/epfl-dlab/aiflows
Project-URL: Issues, https://github.com/epfl-dlab/aiflows/issues
Requires-Python: >=3.10
License-File: LICENSE
Requires-Dist: colorama ==0.4.6
Requires-Dist: pytest ==7.3.1
Requires-Dist: pytest-cov ==4.1.0
Requires-Dist: hydra-core ==1.3.2
Requires-Dist: hydra-colorlog ==1.1.0
Requires-Dist: wrapt-timeout-decorator ==1.3.12.2
Requires-Dist: diskcache ==5.6.1
Requires-Dist: openai ==1.0.0
Requires-Dist: huggingface-hub ==0.19.4
Requires-Dist: jsonlines ==3.1.0
Requires-Dist: jinja2 ==3.1.2
Requires-Dist: mock ==5.0.2
Requires-Dist: rich ==12.6.0
Requires-Dist: litellm ==1.0.0
Requires-Dist: colink ==0.3.7
Requires-Dist: termcolor ==2.4.0
Requires-Dist: streamlit ==1.32.2
